humbletray/__init__.py
humbletray/chromeapp.py
humbletray/layout.py
humbletray/leaf.png
humbletray/main.py
humbletray/systray.py
humbletray/__pyinstaller/__init__.py
humbletray/__pyinstaller/hook-humbletray.py
humbletray-0.0.22.dist-info/LICENSE-APACHE
humbletray-0.0.22.dist-info/LICENSE-MIT
humbletray-0.0.22.dist-info/METADATA
humbletray-0.0.22.dist-info/WHEEL
humbletray-0.0.22.dist-info/entry_points.txt
humbletray-0.0.22.dist-info/top_level.txt
humbletray-0.0.22.dist-info/RECORD
