Metadata-Version: 2.1
Name: humbletray
Version: 0.0.22
Summary: UNKNOWN
Home-page: https://github.com/_/humbletray
Author: Kevin Smith
Author-email: ksmith@99hats.com
Maintainer: Kevin Smith
Maintainer-email: ksmith@99hats.com
License: MIT/Apache-2.0
Platform: UNKNOWN
Classifier: Development Status :: 4 - Beta
Classifier: Intended Audience :: Developers
Classifier: License :: OSI Approved :: MIT License
Classifier: License :: OSI Approved :: Apache Software License
Classifier: Natural Language :: English
Classifier: Operating System :: OS Independent
Classifier: Programming Language :: Python :: 2.7
Classifier: Programming Language :: Python :: 3.5
Classifier: Programming Language :: Python :: 3.6
Classifier: Programming Language :: Python :: Implementation :: CPython
Classifier: Programming Language :: Python :: Implementation :: PyPy
Requires-Dist: schedule
Requires-Dist: justpy
Requires-Dist: pystray
Requires-Dist: loguru
